qsdn/__init__.py
qsdn-0.0.0.dist-info/METADATA
qsdn-0.0.0.dist-info/WHEEL
qsdn-0.0.0.dist-info/top_level.txt
qsdn-0.0.0.dist-info/RECORD
