Metadata-Version: 2.1
Name: qsdn
Version: 0.0.0
Summary: Python Qt5 Classes that Display and Parse Numbers using Standard Decimal Notation
Home-page: https://github.com/shawnpringle/separatorsafterdecimal
Author: Shawn.Pringle
Author-email: shawn.pringle@gmail.com
License: UNKNOWN
Download-URL: https://github.com/shawnpringle/separatorsafterdecimal/archive/v0.0.0.tar.gz
Platform: UNKNOWN
Classifier: Programming Language :: Python :: 3
Classifier: License :: OSI Approved :: MIT License
Classifier: Operating System :: OS Independent
Requires-Dist: PyQt5
